etc/msikeyboard/config.yaml
msikeyboard/__init__.py
msikeyboard/__main__.py
msikeyboard/msikbapi.py
msikeyboard/msikblightd.py
msikeyboard-0.1.1.dist-info/LICENSE.txt
msikeyboard-0.1.1.dist-info/METADATA
msikeyboard-0.1.1.dist-info/RECORD
msikeyboard-0.1.1.dist-info/WHEEL
msikeyboard-0.1.1.dist-info/entry_points.txt
msikeyboard-0.1.1.dist-info/top_level.txt
