Metadata-Version: 2.1
Name: msikeyboard
Version: 0.1.1
Summary: Support library and daemon for SteelSeries keyboards on MSI laptops
Home-page: https://github.com/m0r0zzz/msikeyboard
Author: DeD MorozZz
Author-email: morozzz.g2@gmail.com
Maintainer: DeD MorozZz
Maintainer-email: morozzz.g2@gmail.com
License: GPL-3.0
Keywords: MSI keyboard steelseries backlight
Platform: UNKNOWN
Classifier: License :: OSI Approved :: GNU General Public License v3 (GPLv3)
Classifier: Development Status :: 3 - Alpha
Classifier: Environment :: No Input/Output (Daemon)
Classifier: Intended Audience :: End Users/Desktop
Classifier: Natural Language :: English
Classifier: Operating System :: POSIX :: Linux
Classifier: Programming Language :: Python :: 3
Requires-Dist: dbus-python
Requires-Dist: hidapi-cffi
Requires-Dist: pygobject
Requires-Dist: pyyaml
